3way-1.5.0.42.data/scripts/Freeway
Arsenal/__init__.py
Arsenal/CSALab/CSASpam.py
Arsenal/CSALab/__init__.py
Arsenal/DN/DNFlood.py
Arsenal/DN/__init__.py
Arsenal/DN/dn_utils.py
FreewayTools/__init__.py
FreewayTools/arsenal.py
FreewayTools/audit.py
FreewayTools/beacon_spam.py
FreewayTools/checkmac.py
FreewayTools/colors.py
FreewayTools/deauth.py
FreewayTools/evil_twin.py
FreewayTools/fuzzer.py
FreewayTools/git_downloader.py
FreewayTools/hopper.py
FreewayTools/monitor.py
FreewayTools/pkt_crafter.py
FreewayTools/updater.py
3way-1.5.0.42.dist-info/LICENSE
3way-1.5.0.42.dist-info/METADATA
3way-1.5.0.42.dist-info/WHEEL
3way-1.5.0.42.dist-info/top_level.txt
3way-1.5.0.42.dist-info/RECORD
