Metadata-Version: 2.1
Name: 3way
Version: 1.5.0.42
Summary: Freeway for network pentesting
Home-page: https://github.com/FLOCK4H/Freeway
Author: FLOCK4H
License: MIT
License-File: LICENSE
Requires-Dist: rich
Requires-Dist: scapy
